LICENSE
README.md
pyproject.toml
setup.py
lopata.egg-info/PKG-INFO
lopata.egg-info/SOURCES.txt
lopata.egg-info/dependency_links.txt
lopata.egg-info/requires.txt
lopata.egg-info/top_level.txt
plutus/__init__.py
plutus/backtest.py
plutus/benchmark.py
plutus/calculations.py
plutus/commissions.py
plutus/plots.py
plutus/trade_breaker.py