Metadata-Version: 2.1
Name: lopata
Version: 0.3.3
Summary: plutus is a python package     for backtesting investment decisions using Python 3.6 and above.
Home-page: https://github.com/witmul/plutus_backtest
Author: IlliaBoloto
Author-email: ils.boloto96@gmail.com
License: MIT
Keywords: backtest python stock portfolio trade daytrading finance downside risk management accumulation return profit loss optimization asset security currency crypto futures derivatives test
Platform: UNKNOWN
Classifier: Development Status :: 4 - Beta
Classifier: Intended Audience :: Developers
Classifier: Intended Audience :: Financial and Insurance Industry
Classifier: Topic :: Software Development
Classifier: Topic :: Office/Business :: Financial
Classifier: Programming Language :: Python :: 3.6
Classifier: Programming Language :: Python :: 3.7
Classifier: Programming Language :: Python :: 3.8
Classifier: Programming Language :: Python :: 3.9
Requires-Python: >=3.6.0
License-File: LICENSE
